kickstart_django/__init__.py
kickstart_django/app_updater.py
kickstart_django/cli.py
kickstart_django/setup_django.py
kickstart_django/utils.py
kickstart_django_cli-0.1.0.dist-info/LICENSE
kickstart_django_cli-0.1.0.dist-info/METADATA
kickstart_django_cli-0.1.0.dist-info/WHEEL
kickstart_django_cli-0.1.0.dist-info/entry_points.txt
kickstart_django_cli-0.1.0.dist-info/top_level.txt
kickstart_django_cli-0.1.0.dist-info/RECORD
