Metadata-Version: 2.2
Name: kickstart-django-cli
Version: 0.1.0
Summary: A simple CLI tool to scaffold Django projects
Home-page: https://github.com/Remithrn/django-kickstart-cli
Author: Remith R Nair
Author-email: nair.remith@gmail.com
Classifier: Programming Language :: Python :: 3
Classifier: License :: OSI Approved :: MIT License
Classifier: Operating System :: OS Independent
Requires-Python: >=3.7
License-File: LICENSE
Requires-Dist: rich
Requires-Dist: questionary
Requires-Dist: astor
Dynamic: author
Dynamic: author-email
Dynamic: classifier
Dynamic: description
Dynamic: description-content-type
Dynamic: home-page
Dynamic: requires-dist
Dynamic: requires-python
Dynamic: summary
